{
	"recommendations": [
		{
			"image": "/company/experian.webp",
			"name": "Analista de Soporte D.A",
			"date": "sep. 2023 · Actualidad",
			"title": "Experian",
			"message": "Aptitudes: Docker · Jenkins · Bitbucket · Git · Linux · Shell Script · Pipelines."
		},
		{
			"image": "/company/comware.webp",
			"name": "Analista Vertical Nivel I",
			"date": "ene. 2023 - sep. 2023 · 9 meses",
			"title": "ComWare S.A",
			"message": "Aptitudes: SIP Trunking · Híbrido de fibra coaxial · Voz sobre IP (VoIP) · Enrutadores · LAN-WAN · Redes MPLS · Redes de fibra óptica · Routers de Cisco."
		},
		{
			"image": "/company/emtelco.webp",
			"name": "Analista de soporte I.T Nivel 2",
			"date": "mar. 2021 - dic. 2022 · 1 año 10 meses",
			"title": "Emtelco",
			"message": "Aptitudes: Híbrido de fibra coaxial · Voz sobre IP (VoIP) · Red de cobre · LAN-WAN · Redes de fibra óptica · Routers de Cisco."
		},
		{
			"image": "/company/smso.webp",
			"name": "Técnico de soporte I.T",
			"date": "oct. 2019 - oct. 2020 · 1 año 1 mes",
			"title": "Servicios especiales SMSO",
			"message": "Aptitudes: Cámaras IP · Tecnología de Cisco · LAN-WAN · Windows · Linux."
		},
		{
			"image": "/company/liteyca.webp",
			"name": "Técnico de telecomunicaciones",
			"date": "feb. 2016 - jun. 2018 · 2 años 5 meses",
			"title": "Liteyca Telecomunicaciones",
			"message": "Aptitudes: Red óptica pasiva con capacidad de gigabit · Redes de fibra óptica."
		},
		{
			"image": "/company/fscr.webp",
			"name": "Técnico de telecomunicaciones",
			"date": "jun. 2015 - feb. 2016 · 9 meses",
			"title": "FSCR INGENIERIA SAS",
			"message": "Aptitudes: Red de cobre · Redes de fibra óptica."
		},
		{
			"image": "/company/comsat.webp",
			"name": "Técnico de Sistemas Satelitales",
			"date": "oct. 2014 - abr. 2015 · 7 meses",
			"title": "Comsat",
			"message": "Aptitudes: Sistemas satelitales · Red de cobre."
		}
	]
}
